{
    "titre_video": "Et Si On Mourrait Tous à 30 ans ?! (en 360s)",
    "description_video": "La vie est trop courte… surtout lorsqu’elle ne dure que 30 ans !\nPour essayer NordVPN, c'est juste ici : http://nordvpn.com/poisson\n\n♣ Instagram : https://www.instagram.com/poissonfecond\n♥ Facebook : https://www.facebook.com/PoissonFecond\n♠ Twitter : https://twitter.com/PoissonFecond\n\nSOURCES :\n**********************************\n\nAge moyen de parentalité en France :\nhttps://www.insee.fr/fr/statistiques/1281068\nhttps://www.lexpress.fr/actualite/societe/a-quel-age-le-1er-enfant_952276.html\n\nDéfinition de l’âge médian :\nhttps://fr.wikipedia.org/wiki/%C3%82ge_m%C3%A9dian\n\nSur la démographie française :\nhttps://fr.statista.com/statistiques/472349/repartition-population-groupe-dage-france/\nhttps://fr.wikipedia.org/wiki/D%C3%A9mographie_de_la_France\nhttps://www.insee.fr/fr/accueil\n\nSur la démographie mondiale :\nhttps://www.la-croix.com/Actualite/Monde/L-humanite-termine-sa-transition-demographique-2014-07-10-1177362\n\nSur l’Afrique Sub-Saharienne et sa démographie :\nhttps://en.unesco.org/gem-report/sites/gem-report/files/157229F.pdf\nhttps://regardexcentrique.files.wordpress.com/2017/04/180114carteafriquedc3a9mocratiesdictaturestcii-2017-rmarzin.jpg\nhttp://www.rfi.fr/hebdo/20170331-demographie-jeunesse-africaine-risque-potentiel\nhttps://www.lemonde.fr/afrique/article/2016/07/21/demographie-africaine-les-bons-comptes-feront-les-bons-pays_4972907_3212.html\nhttps://www.monde-diplomatique.fr/2015/11/LERIDON/54200\n\nMUSIQUES :\n**********************************\n♫ Weapon Of Impact : Bonnie Grace\n♫ Sunday Banjo : Stationary Sign\n♫ Raw : Freak Kitchen\n♫ Play That Funky Music : Wild Cherry\n♫ The Beginning Of An Era : Bonnie Grace\n♫ The Administrator : Wendel Scherer\n♫ Mission Snow : Wendel Scherer\n♫ Security Breach : Jon Summer\n♫ Humanity : Francis Wells\n♫ Funny Times 3 : Martin Klem\n♫ No Time For Caution : Hans Zimmer\n\nMerci à Charles Picard & Eric Lassalle pour leur aide mature à la réalisation ♥",
    "date_publication": "2019-07-27T18:30:32Z",
    "canal": "Poisson Fécond",
    "vue_count": "1032619",
    "like_count": "56218",
    "comment_count": "2998"
}